vectorama/__init__.py
vectorama/api/__init__.py
vectorama/api/api_pb2.py
vectorama/api/api_pb2.pyi
vectorama/api/api_pb2_grpc.py
vectorama/api/api_pb2_grpc.pyi
vectorama/base.py
vectorama/client.py
vectorama/config.py
vectorama/fields.py
vectorama/parsers.py
vectorama/py.typed
vectorama/query.py
vectorama/tests/__init__.py
vectorama/tests/conftest.py
vectorama/tests/fixtures.py
vectorama/tests/test_client.py
vectorama/tests/test_parsers.py
vectorama/tests/test_query.py
vectorama/utils.py
vectorama-0.1.6.dist-info/METADATA
vectorama-0.1.6.dist-info/WHEEL
vectorama-0.1.6.dist-info/RECORD
