Metadata-Version: 2.1
Name: vectorama
Version: 0.1.6
Summary: 
License: MIT
Author: Pierce Freeman
Author-email: pierce@freeman.vc
Requires-Python: >=3.10,<4.0
Classifier: License :: OSI Approved :: MIT License
Classifier: Programming Language :: Python :: 3
Classifier: Programming Language :: Python :: 3.10
Classifier: Programming Language :: Python :: 3.11
Requires-Dist: pydantic (>=2.2.0,<3.0.0)
